ncs/__init__.py
ncs/call_strategy/__init__.py
ncs/call_strategy/random_action.csv
ncs/call_strategy/random_strategy_portfolio.parquet
ncs/call_strategy/random_strategy_portfolio_10d.parquet
ncs/call_strategy/random_strategy_portfolio_1d.parquet
ncs/call_strategy/random_strategy_portfolio_5d.parquet
ncs/call_strategy/spy_action.csv
ncs/call_strategy/spy_strategy_portfolio.parquet
ncs/call_strategy/strategy.py
ncs/data/__init__.py
ncs/data/downloader.py
ncs/model/__init__.py
ncs/model/config.py
ncs/model/inference.py
ncs/model/train.py
rotman_ncs-0.1.0a8.dist-info/LICENSE
rotman_ncs-0.1.0a8.dist-info/METADATA
rotman_ncs-0.1.0a8.dist-info/WHEEL
rotman_ncs-0.1.0a8.dist-info/top_level.txt
rotman_ncs-0.1.0a8.dist-info/RECORD
