Metadata-Version: 2.1
Name: rotman-ncs
Version: 0.1.0a8
Summary: UoT Rotman NLP Case Study
Home-page: https://github.com/colingwuyu/rotman_ncs.git
Author: Zeyu Colin Wang
Author-email: colinzeyu.wang@utoronto.ca
Keywords: NLP,Case Study,UoT,UoT Rotman,Machine Learning,Investing
Classifier: Programming Language :: Python :: 3.8
Classifier: Programming Language :: Python :: 3.9
Classifier: Programming Language :: Python :: 3.10
Classifier: License :: OSI Approved :: MIT License
Classifier: Operating System :: OS Independent
Requires-Python: >=3.8
License-File: LICENSE
Requires-Dist: numpy (>=1.24.4)
Requires-Dist: unidecode (==1.3.6)
Requires-Dist: textblob (==0.17.1)
Requires-Dist: pandas (>=2.0.0)
Requires-Dist: tqdm (>=4.65.0)
Requires-Dist: nltk (==3.8.1)
Requires-Dist: scikit-learn (==1.3.0)
Requires-Dist: contractions (==0.1.73)
Requires-Dist: pyarrow (>=12.0.1)
Requires-Dist: spacy (==3.5.4)
Requires-Dist: plotly (==5.15.0)
Requires-Dist: gensim (==4.3.1)
Requires-Dist: transformers (==4.30.2)
Requires-Dist: kaleido (==0.2.1)
Requires-Dist: ipykernel (==6.24.0)
Requires-Dist: nbformat (==5.9.0)
